{
  "AWSTemplateFormatVersion" : "2010-09-09",

  "Description" : "Create an ec2 instance that automatically starts httpd. **WARNING** This template creates one or more Amazon EC2 instances. You will be billed for the AWS resources used if you create a stack from this template.",

  "Parameters" : {
    "InstanceType" : {
      "Description" : "Type of EC2 instance to launch",
      "Type" : "String",
      "Default" : "t1.micro"
    },
    "WebServerPort" : {
      "Description" : "TCP/IP port of the web server",
      "Type" : "String",
      "Default" : "80"
    },
    "KeyName" : {
      "Description" : "Name of an existing EC2 KeyPair to enable SSH access to the instances",
      "Type" : "AWS::EC2::KeyPair::KeyName",
      "ConstraintDescription" : "must be the name of an existing EC2 KeyPair.",
      "Default" : "mike"
    }
  },

  "Mappings" : {
    "AWSInstanceType2Arch" : {
      "t1.micro"    : { "Arch" : "PV64"   },
      "t2.micro"    : { "Arch" : "HVM64"  },
      "t2.small"    : { "Arch" : "HVM64"  },
      "t2.medium"   : { "Arch" : "HVM64"  },
      "m1.small"    : { "Arch" : "PV64"   },
      "m1.medium"   : { "Arch" : "PV64"   },
      "m1.large"    : { "Arch" : "PV64"   },
      "m1.xlarge"   : { "Arch" : "PV64"   },
      "m2.xlarge"   : { "Arch" : "PV64"   },
      "m2.2xlarge"  : { "Arch" : "PV64"   },
      "m2.4xlarge"  : { "Arch" : "PV64"   },
      "m3.medium"   : { "Arch" : "HVM64"  },
      "m3.large"    : { "Arch" : "HVM64"  },
      "m3.xlarge"   : { "Arch" : "HVM64"  },
      "m3.2xlarge"  : { "Arch" : "HVM64"  },
      "c1.medium"   : { "Arch" : "PV64"   },
      "c1.xlarge"   : { "Arch" : "PV64"   },
      "c3.large"    : { "Arch" : "HVM64"  },
      "c3.xlarge"   : { "Arch" : "HVM64"  },
      "c3.2xlarge"  : { "Arch" : "HVM64"  },
      "c3.4xlarge"  : { "Arch" : "HVM64"  },
      "c3.8xlarge"  : { "Arch" : "HVM64"  },
      "g2.2xlarge"  : { "Arch" : "HVMG2"  },
      "r3.large"    : { "Arch" : "HVM64"  },
      "r3.xlarge"   : { "Arch" : "HVM64"  },
      "r3.2xlarge"  : { "Arch" : "HVM64"  },
      "r3.4xlarge"  : { "Arch" : "HVM64"  },
      "r3.8xlarge"  : { "Arch" : "HVM64"  },
      "i2.xlarge"   : { "Arch" : "HVM64"  },
      "i2.2xlarge"  : { "Arch" : "HVM64"  },
      "i2.4xlarge"  : { "Arch" : "HVM64"  },
      "i2.8xlarge"  : { "Arch" : "HVM64"  },
      "hi1.4xlarge" : { "Arch" : "HVM64"  },
      "hs1.8xlarge" : { "Arch" : "HVM64"  },
      "cr1.8xlarge" : { "Arch" : "HVM64"  },
      "cc2.8xlarge" : { "Arch" : "HVM64"  }
    },

    "AWSRegionArch2AMI" : {
      "us-east-1"      : { "PV64" : "ami-50842d38", "HVM64" : "ami-08842d60", "HVMG2" : "ami-3a329952"  },
      "us-west-2"      : { "PV64" : "ami-af86c69f", "HVM64" : "ami-8786c6b7", "HVMG2" : "ami-47296a77"  },
      "us-west-1"      : { "PV64" : "ami-c7a8a182", "HVM64" : "ami-cfa8a18a", "HVMG2" : "ami-331b1376"  },
      "eu-west-1"      : { "PV64" : "ami-aa8f28dd", "HVM64" : "ami-748e2903", "HVMG2" : "ami-00913777"  },
      "ap-southeast-1" : { "PV64" : "ami-20e1c572", "HVM64" : "ami-d6e1c584", "HVMG2" : "ami-fabe9aa8"  },
      "ap-northeast-1" : { "PV64" : "ami-21072820", "HVM64" : "ami-35072834", "HVMG2" : "ami-5dd1ff5c"  },
      "ap-southeast-2" : { "PV64" : "ami-8b4724b1", "HVM64" : "ami-fd4724c7", "HVMG2" : "ami-e98ae9d3"  },
      "sa-east-1"      : { "PV64" : "ami-9d6cc680", "HVM64" : "ami-956cc688", "HVMG2" : "NOT_SUPPORTED" },
      "cn-north-1"     : { "PV64" : "ami-a857c591", "HVM64" : "ami-ac57c595", "HVMG2" : "NOT_SUPPORTED" },
      "eu-central-1"   : { "PV64" : "ami-a03503bd", "HVM64" : "ami-b43503a9", "HVMG2" : "ami-b03503ad"  }
    }
  },

  "Resources" : {
    "Ec2Instance1" : {
      "Type" : "AWS::EC2::Instance",

      "Metadata" : {
        "Comment1" : "Configure the bootstrap helpers to install the Apache Web Server and PHP",
        "Comment2" : "Save website content to /var/www/html/index.php",

        "AWS::CloudFormation::Init" : {
          "configSets" : {
            "Install" : [ "Install" ]
          },

          "Install" : {
            "packages" : {
              "yum" : {
                "httpd"        : [],
                "php"          : []
              }
            },

            "files" : {
              "/var/www/html/index.php" : {
                "content" : { "Fn::Join" : [ "", [
                  "<html>\n",
                  "  <head>\n",
                  "    <title>AWS CloudFormation Sample</title>\n",
                  "    <meta http-equiv=\"Content-Type\" content=\"text/html; charset=ISO-8859-1\">\n",
                  "  </head>\n",
                  "  <body>\n",
                  "    <h1>Automation For The People!</h1>\n",
                  "    <p/>\n",
                  "    <?php\n",
                  "      // Print out the current data and time\n",
                  "      print \"The Current Date and Time is: <br/>\";\n",
                  "      print date(\"g:i A l, F j Y.\");\n",
                  "    ?>\n",
                  "    <p/>\n",
                  "    <?php\n",
                  "      // Setup a handle for CURL\n",
                  "      $curl_handle=curl_init();\n",
                  "      curl_setopt($curl_handle,CURLOPT_CONNECTTIMEOUT,2);\n",
                  "      curl_setopt($curl_handle,CURLOPT_RETURNTRANSFER,1);\n",
                  "      // Get the hostname of the intance from the instance metadata\n",
                  "      curl_setopt($curl_handle,CURLOPT_URL,'http://169.254.169.254/latest/meta-data/public-hostname');\n",
                  "      $hostname = curl_exec($curl_handle);\n",
                  "      if (empty($hostname))\n",
                  "      {\n",
                  "        print \"Sorry, for some reason, we got no hostname back <br />\";\n",
                  "      }\n",
                  "      else\n",
                  "      {\n",
                  "        print \"Server = \" . $hostname . \"<br />\";\n",
                  "      }\n",
                  "      // Get the instance-id of the intance from the instance metadata\n",
                  "      curl_setopt($curl_handle,CURLOPT_URL,'http://169.254.169.254/latest/meta-data/instance-id');\n",
                  "      $instanceid = curl_exec($curl_handle);\n",
                  "      if (empty($instanceid))\n",
                  "      {\n",
                  "        print \"Sorry, for some reason, we got no instance id back <br />\";\n",
                  "      }\n",
                  "      else\n",
                  "      {\n",
                  "        print \"EC2 instance-id = \" . $instanceid . \"<br />\";\n",
                  "      }\n",
                  "    ?>\n",
                  "    <h2>PHP Information</h2>\n",
                  "    <p/>\n",
                  "    <?php\n",
                  "      phpinfo();\n",
                  "    ?>\n",
                  "  </body>\n",
                  "</html>\n"
                ]]},
                "mode"  : "000600",
                "owner" : "apache",
                "group" : "apache"
              }
            },

            "services" : {
              "sysvinit" : {  
                "httpd"   : { "enabled" : "true", "ensureRunning" : "true" }
              }
            }
          }
        }
      },

      "Properties" : {
        "SecurityGroups" : [ { "Ref" : "InstanceSecurityGroup" } ],
        "KeyName" : { "Ref" : "KeyName" },
        "ImageId" : { "Fn::FindInMap" : [ "AWSRegionArch2AMI", { "Ref" : "AWS::Region" },
                                          { "Fn::FindInMap" : [ "AWSInstanceType2Arch", { "Ref" : "InstanceType" },
                                          "Arch" ] } ] },
        "UserData"       : { "Fn::Base64" : { "Fn::Join" : ["", [
                    "#!/bin/bash -xe\n",
                    "yum update aws-cfn-bootstrap\n",
                    "# Install the files and packages from the metadata\n",
                    "/opt/aws/bin/cfn-init ",
                    "         --stack ", { "Ref" : "AWS::StackName" },
                    "         --resource Ec2Instance1 ",
                    "         --configsets Install ",
                    "         --region ", { "Ref" : "AWS::Region" }, "\n",
                    "\n",
                    "# Signal the status from cfn-init\n",
                    "/opt/aws/bin/cfn-signal -e $? ",
                    "         --stack ", { "Ref" : "AWS::StackName" },
                    "         --resource Ec2Instance1 ",
                    "         --region ", { "Ref" : "AWS::Region" }, "\n"
        ]]}}
      },

      "CreationPolicy" : {
        "ResourceSignal" : {
          "Timeout" : "PT5M"
        }
      }
    },

    "IPAddress1" : {
      "Type" : "AWS::EC2::EIP"
    },

    "IPAssoc1" : {
      "Type" : "AWS::EC2::EIPAssociation",
      "Properties" : {
        "InstanceId" : { "Ref" : "Ec2Instance1" },
        "EIP" : { "Ref" : "IPAddress1" }
      }
    },

    "InstanceSecurityGroup" : {
      "Type" : "AWS::EC2::SecurityGroup",
      "Properties" : {
        "GroupDescription" : "Enable SSH access and HTTP access on the inbound port",
        "SecurityGroupIngress" : [ {
          "IpProtocol" : "tcp",
          "FromPort" : "22",
          "ToPort" : "22",
          "CidrIp" : "0.0.0.0/0"
        },
        {
          "IpProtocol" : "tcp",
          "FromPort" : { "Ref" : "WebServerPort" },
          "ToPort" : { "Ref" : "WebServerPort" },
          "CidrIp" : "0.0.0.0/0"
        } ]
      }
    }
  },

  "Outputs" : {
    "URL" : {
      "Description" : "URL of the sample website",
      "Value" :  { "Fn::Join" : [ "", [ "http://", { "Ref" : "IPAddress1" }]]}
    },
    "IP1" : {
      "Description" : "Public IP of first EC2 instance",
      "Value" : { "Ref" : "IPAddress1" }
    }
  }
}

